pcpartpicker/__init__.py
pcpartpicker/api.py
pcpartpicker/errors.py
pcpartpicker/handler.py
pcpartpicker/mappings.py
pcpartpicker/parse_utils.py
pcpartpicker/part_data.py
pcpartpicker/parts.py
pcpartpicker/scraper.py
pcpartpicker/utils.py
pcpartpicker-2.2.2.dist-info/LICENSE
pcpartpicker-2.2.2.dist-info/METADATA
pcpartpicker-2.2.2.dist-info/WHEEL
pcpartpicker-2.2.2.dist-info/top_level.txt
pcpartpicker-2.2.2.dist-info/RECORD
