Metadata-Version: 2.1
Name: pcpartpicker
Version: 2.2.2
Summary: A fast, simple API for PCPartPicker.com.
Home-page: https://github.com/JonathanVusich/pcpartpicker
Author: Jonathan Vusich
Author-email: jonathanvusich@gmail.com
License: GPL
Keywords: pcpartpicker api webscraper python3
Platform: UNKNOWN
Classifier: Development Status :: 5 - Production/Stable
Classifier: Topic :: Utilities
Classifier: License :: OSI Approved :: GNU General Public License v3 (GPLv3)
